[
  {
    "FechaPrestamo": "2024-01-06",
    "FechaEntrega": "2024-02-06",
    "Estado": "Pendiente",
    "Cliente": "Enmanuel",
    "Libro": "Juanchi"
  },
  {
    "FechaPrestamo": "2024-05-12",
    "FechaEntrega": "2024-06-12",
    "Estado": "Entregado",
    "Cliente": "Juan",
    "Libro": "El Herrero"
  },
  {
    "FechaPrestamo": "2024-01-12",
    "FechaEntrega": "2024-02-12",
    "Estado": "Reportado",
    "Cliente": "Camilo",
    "Libro": "Caballo"
  },
  {
    "FechaPrestamo": "2024-03-16",
    "FechaEntrega": "2024-06-06",
    "Estado": "Pendiente",
    "Cliente": "Tomas",
    "Libro": "Faran Jutini"
  },
  {
    "FechaPrestamo": "2024-05-26",
    "FechaEntrega": "2024-07-06",
    "Estado": "Pendiente",
    "Cliente": "Julia",
    "Libro": "Lucas"
  },
  {
    "FechaPrestamo": "2024-02-15",
    "FechaEntrega": "2024-03-15",
    "Estado": "Entregado",
    "Cliente": "Ana",
    "Libro": "El Principito"
  },
  {
    "FechaPrestamo": "2024-03-01",
    "FechaEntrega": "2024-03-31",
    "Estado": "Pendiente",
    "Cliente": "Pedro",
    "Libro": "Cien Años de Soledad"
  },
  {
    "FechaPrestamo": "2024-01-20",
    "FechaEntrega": "2024-02-20",
    "Estado": "Renovado",
    "Cliente": "María",
    "Libro": "Harry Potter y la Piedra Filosofal"
  },
  {
    "FechaPrestamo": "2024-02-05",
    "FechaEntrega": "2024-03-05",
    "Estado": "Retrasado",
    "Cliente": "Juan",
    "Libro": "El Hobbit"
  },
  {
    "FechaPrestamo": "2024-03-10",
    "FechaEntrega": "2024-04-10",
    "Estado": "Pendiente",
    "Cliente": "Rosa",
    "Libro": "Los Juegos del Hambre"
  }
]
